iati2json-0.1.3.dist-info/METADATA
iati2json-0.1.3.dist-info/WHEEL
iati2json-0.1.3.dist-info/license_files/LICENSE
iati2json/__init__.py
iati2json/iati2json.cpython-311-darwin.so
iati2json-0.1.3.dist-info/RECORD
