Metadata-Version: 2.1
Name: iati2json
Version: 0.1.3
Requires-Dist: xmlschema
Requires-Dist: pytest; extra == 'dev'
Provides-Extra: dev
License-File: LICENSE
Summary: Iati to JSON converter
License: MIT
